qilimanjaroq_client/__init__.py
qilimanjaroq_client/api.py
qilimanjaroq_client/config.py
qilimanjaroq_client/connection.py
qilimanjaroq_client/errors.py
qilimanjaroq_client/job.py
qilimanjaroq_client/job_result.py
qilimanjaroq_client/user.py
qilimanjaroq_client/util.py
qilimanjaroq_client/devices/__init__.py
qilimanjaroq_client/devices/device.py
qilimanjaroq_client/devices/devices.py
qilimanjaroq_client/devices/quantum_device.py
qilimanjaroq_client/devices/quantum_device_calibration_details.py
qilimanjaroq_client/devices/quantum_device_characteristics.py
qilimanjaroq_client/devices/simulator_device.py
qilimanjaroq_client/devices/simulator_device_characteristics.py
qilimanjaroq_client/tests/__init__.py
qilimanjaroq_client/tests/data.py
qilimanjaroq_client/tests/test_algorithm.py
qilimanjaroq_client/tests/test_device.py
qilimanjaroq_client/tests/test_job.py
qilimanjaroq_client/tests/test_job_result.py
qilimanjaroq_client/tests/test_user.py
qilimanjaroq_client/tests/test_util.py
qilimanjaroq_client/typings/__init__.py
qilimanjaroq_client/typings/algorithm.py
qilimanjaroq_client/typings/auth_config.py
qilimanjaroq_client/typings/connection.py
qilimanjaroq_client/typings/device.py
qilimanjaroq_client/typings/job.py
qilimanjaroq_client-0.0.1.dist-info/LICENSE
qilimanjaroq_client-0.0.1.dist-info/METADATA
qilimanjaroq_client-0.0.1.dist-info/WHEEL
qilimanjaroq_client-0.0.1.dist-info/top_level.txt
qilimanjaroq_client-0.0.1.dist-info/RECORD
